{
  "title": "Image AI models now drive app growth, beating chatbot upgrades",
  "slides": [
    "Image AI boosts installs more than chatbots",
    "Visual content drives user engagement",
    "Better retention, fewer upgrades needed",
    "Add image personalization to your app",
    "Spotify saw 30% lift with AI covers"
  ],
  "thread_text": [
    "Le tue app perdono utenti? Forse stai usando lo strumento sbagliato.",
    "Chatbot testo? Bello, ma non abbastanza. Le immagini AI spingono le installazioni molto di più.",
    "I contenuti visivi tengono incollati. Non servono mille aggiornamenti per fidelizzare.",
    "La personalizzazione delle immagini nell'app cambia tutto. Ritenzione senza sforzo.",
    "Spotify l’ha fatto: +30% con copertine AI. Stai ancora perdendo l’occasione?"
  ],
  "video_script": [
    "Hai presente le app che non decollano?",
    "Il problema non è il prodotto.",
    "Usi chatbot? Sbagliato.",
    "Le immagini AI funzionano meglio.",
    "Più installazioni, zero fatica.",
    "Spotify ha alzato tutto del 30%.",
    "Immagini personalizzate tengono gli utenti.",
    "Niente aggiornamenti continui.",
    "Copia quel che funziona.",
    "Adesso tocca a te."
  ],
  "savedAt": "2026-05-05T17:20:36.578Z"
}